LICENSE
README.md
setup.py
call_sequencer/__init__.py
call_sequencer/call_sequencer.py
call_sequencer/code_runner.py
call_sequencer/markdown_extractors.py
call_sequencer.egg-info/PKG-INFO
call_sequencer.egg-info/SOURCES.txt
call_sequencer.egg-info/dependency_links.txt
call_sequencer.egg-info/top_level.txt
test/test_executor.py
test/test_main.py