Metadata-Version: 2.1
Name: call-sequencer
Version: 1.0.4
Summary: A Python package for sequencing function calls as blocks
Home-page: https://github.com/SujalChoudhari/call-sequencer
Author: Sjal Choudhari
Author-email: sjlchoudhari@gmail.com
Classifier: Programming Language :: Python :: 3
Classifier: License :: OSI Approved :: MIT License
Classifier: Operating System :: OS Independent
License-File: LICENSE
